pfconclient/__init__.py
pfconclient/__main__.py
pfconclient/client.py
pfconclient/exceptions.py
python_pfconclient-3.3.0.dist-info/licenses/LICENSE
python_pfconclient-3.3.0.dist-info/METADATA
python_pfconclient-3.3.0.dist-info/WHEEL
python_pfconclient-3.3.0.dist-info/entry_points.txt
python_pfconclient-3.3.0.dist-info/top_level.txt
python_pfconclient-3.3.0.dist-info/RECORD
