Metadata-Version: 2.4
Name: python-pfconclient
Version: 3.3.0
Summary: (Python) client for the Pfcon API
Author-email: FNNDSC <dev@babymri.org>
License-Expression: MIT
Project-URL: Homepage, https://github.com/FNNDSC/python-pfconclient
Classifier: Programming Language :: Python :: 3
Classifier: Operating System :: OS Independent
Requires-Python: >=3.11
License-File: LICENSE
Requires-Dist: requests>=2.27.1
Provides-Extra: dev
Requires-Dist: pytest; extra == "dev"
Requires-Dist: ruff; extra == "dev"
Dynamic: license-file
